[
    {
        "round": 1,
        "score": 0.36666666666666664,
        "avg_cost": 0.009080041666666667,
        "total_cost": 0.5448025,
        "time": "2026-03-23T16:25:21.226679"
    },
    {
        "round": 2,
        "score": 0.4166666666666667,
        "avg_cost": 0.02183041666666666,
        "total_cost": 1.3098249999999996,
        "time": "2026-03-23T16:27:19.657820"
    },
    {
        "round": 3,
        "score": 0.3333333333333333,
        "avg_cost": 0.02167508333333333,
        "total_cost": 1.3005049999999998,
        "time": "2026-03-23T16:28:39.370630"
    },
    {
        "round": 4,
        "score": 0.31666666666666665,
        "avg_cost": 0.031335416666666664,
        "total_cost": 1.880125,
        "time": "2026-03-23T16:30:36.744209"
    },
    {
        "round": 5,
        "score": 0.36666666666666664,
        "avg_cost": 0.021844958333333327,
        "total_cost": 1.3106974999999996,
        "time": "2026-03-23T16:32:04.962475"
    },
    {
        "round": 6,
        "score": 0.38333333333333336,
        "avg_cost": 0.022359458333333325,
        "total_cost": 1.3415674999999996,
        "time": "2026-03-23T16:34:02.625640"
    },
    {
        "round": 7,
        "score": 0.4166666666666667,
        "avg_cost": 0.023070916666666663,
        "total_cost": 1.3842549999999998,
        "time": "2026-03-23T16:35:22.045522"
    },
    {
        "round": 9,
        "score": 0.3,
        "avg_cost": 0.033084791666666676,
        "total_cost": 1.9850875000000003,
        "time": "2026-03-23T16:37:41.712132"
    },
    {
        "round": 10,
        "score": 0.38333333333333336,
        "avg_cost": 0.033738625,
        "total_cost": 2.0243175,
        "time": "2026-03-23T16:39:41.962194"
    },
    {
        "round": 11,
        "score": 0.4,
        "avg_cost": 0.03372691666666665,
        "total_cost": 2.023614999999999,
        "time": "2026-03-23T16:42:05.727624"
    },
    {
        "round": 12,
        "score": 0.31666666666666665,
        "avg_cost": 0.033039875,
        "total_cost": 1.9823925000000002,
        "time": "2026-03-23T16:43:55.641323"
    },
    {
        "round": 13,
        "score": 0.0,
        "avg_cost": 0.0,
        "total_cost": 0.0,
        "time": "2026-03-23T16:44:17.185778"
    },
    {
        "round": 14,
        "score": 0.2833333333333333,
        "avg_cost": 0.025947458333333326,
        "total_cost": 1.5568474999999995,
        "time": "2026-03-23T16:46:22.765103"
    },
    {
        "round": 15,
        "score": 0.4,
        "avg_cost": 0.03277191666666667,
        "total_cost": 1.9663150000000005,
        "time": "2026-03-23T16:48:27.161677"
    },
    {
        "round": 16,
        "score": 0.31666666666666665,
        "avg_cost": 0.023867458333333338,
        "total_cost": 1.4320475000000004,
        "time": "2026-03-23T16:49:54.991339"
    }
]